README.txt
setup.cfg
setup.py
FileFields.egg-info/PKG-INFO
FileFields.egg-info/SOURCES.txt
FileFields.egg-info/dependency_links.txt
FileFields.egg-info/entry_points.txt
FileFields.egg-info/not-zip-safe
FileFields.egg-info/requires.txt
FileFields.egg-info/top_level.txt
file_fields/__init__.py
file_fields/controllers.py
file_fields/release.py
file_fields/widgets/__init__.py
file_fields/widgets/demo.py
file_fields/widgets/file_field.py
file_fields/widgets/file_field_desc.kid
file_fields/widgets/image_field.py
file_fields/widgets/image_field_desc.kid
file_fields/widgets/master.kid